{"errors":[],"warnings":[],"namedChunkGroups":{"app":{"chunks":[15,5],"assets":["webpack-runtime-2a6f68dc67aea08bf991.js","webpack-runtime-2a6f68dc67aea08bf991.js.map","app-f94ae40fe74996f430c9.js","app-f94ae40fe74996f430c9.js.map"],"children":{},"childAssets":{}},"component---src-templates-post-jsx":{"chunks":[0,1,2,16,12],"assets":["styles.b004dd8d4d17221ed601.css","styles-5767387eccded947114a.js","styles-5767387eccded947114a.js.map","1-2dce45b6c53bff1bbba8.js","1-2dce45b6c53bff1bbba8.js.map","2-4aefba31d5b56627ae14.js","2-4aefba31d5b56627ae14.js.map","16-666c10685e60702f38b2.js","16-666c10685e60702f38b2.js.map","component---src-templates-post-jsx-b674d58c0a60dbcb822f.js","component---src-templates-post-jsx-b674d58c0a60dbcb822f.js.map"],"children":{},"childAssets":{}},"component---src-templates-tag-jsx":{"chunks":[0,1,2,3,13],"assets":["styles.b004dd8d4d17221ed601.css","styles-5767387eccded947114a.js","styles-5767387eccded947114a.js.map","1-2dce45b6c53bff1bbba8.js","1-2dce45b6c53bff1bbba8.js.map","2-4aefba31d5b56627ae14.js","2-4aefba31d5b56627ae14.js.map","3-617b385cf3249e7667b6.js","3-617b385cf3249e7667b6.js.map","component---src-templates-tag-jsx-2af747ec75d0e3fd3490.js","component---src-templates-tag-jsx-2af747ec75d0e3fd3490.js.map"],"children":{},"childAssets":{}},"component---src-templates-category-jsx":{"chunks":[0,1,2,3,11],"assets":["styles.b004dd8d4d17221ed601.css","styles-5767387eccded947114a.js","styles-5767387eccded947114a.js.map","1-2dce45b6c53bff1bbba8.js","1-2dce45b6c53bff1bbba8.js.map","2-4aefba31d5b56627ae14.js","2-4aefba31d5b56627ae14.js.map","3-617b385cf3249e7667b6.js","3-617b385cf3249e7667b6.js.map","component---src-templates-category-jsx-157bacaf24236da2ba68.js","component---src-templates-category-jsx-157bacaf24236da2ba68.js.map"],"children":{},"childAssets":{}},"component---src-templates-about-jsx":{"chunks":[0,1,10],"assets":["styles.b004dd8d4d17221ed601.css","styles-5767387eccded947114a.js","styles-5767387eccded947114a.js.map","1-2dce45b6c53bff1bbba8.js","1-2dce45b6c53bff1bbba8.js.map","component---src-templates-about-jsx-3755af25d0144ff749d4.js","component---src-templates-about-jsx-3755af25d0144ff749d4.js.map"],"children":{},"childAssets":{}},"component---src-pages-blog-jsx":{"chunks":[0,1,2,3,6],"assets":["styles.b004dd8d4d17221ed601.css","styles-5767387eccded947114a.js","styles-5767387eccded947114a.js.map","1-2dce45b6c53bff1bbba8.js","1-2dce45b6c53bff1bbba8.js.map","2-4aefba31d5b56627ae14.js","2-4aefba31d5b56627ae14.js.map","3-617b385cf3249e7667b6.js","3-617b385cf3249e7667b6.js.map","component---src-pages-blog-jsx-899d090f3229500a45b3.js","component---src-pages-blog-jsx-899d090f3229500a45b3.js.map"],"children":{},"childAssets":{}},"component---src-pages-contact-jsx":{"chunks":[0,1,4,17,7],"assets":["styles.b004dd8d4d17221ed601.css","styles-5767387eccded947114a.js","styles-5767387eccded947114a.js.map","1-2dce45b6c53bff1bbba8.js","1-2dce45b6c53bff1bbba8.js.map","4-475dab03c6ac083504a6.js","4-475dab03c6ac083504a6.js.map","17-770f5289fa9f53f65f88.js","17-770f5289fa9f53f65f88.js.map","component---src-pages-contact-jsx-cc8ecbea0ae01bc744fc.js","component---src-pages-contact-jsx-cc8ecbea0ae01bc744fc.js.map"],"children":{},"childAssets":{}},"component---src-pages-index-jsx":{"chunks":[0,1,4,20,8],"assets":["styles.b004dd8d4d17221ed601.css","styles-5767387eccded947114a.js","styles-5767387eccded947114a.js.map","1-2dce45b6c53bff1bbba8.js","1-2dce45b6c53bff1bbba8.js.map","4-475dab03c6ac083504a6.js","4-475dab03c6ac083504a6.js.map","20-81f54fec9d476b38d4d9.js","20-81f54fec9d476b38d4d9.js.map","component---src-pages-index-jsx-13b1b4ed693638807161.js","component---src-pages-index-jsx-13b1b4ed693638807161.js.map"],"children":{},"childAssets":{}},"component---src-pages-resume-jsx":{"chunks":[0,1,18,9],"assets":["styles.b004dd8d4d17221ed601.css","styles-5767387eccded947114a.js","styles-5767387eccded947114a.js.map","1-2dce45b6c53bff1bbba8.js","1-2dce45b6c53bff1bbba8.js.map","18-13d57edf398610c1aa01.js","18-13d57edf398610c1aa01.js.map","component---src-pages-resume-jsx-7a1eb7995620c0320d38.js","component---src-pages-resume-jsx-7a1eb7995620c0320d38.js.map"],"children":{},"childAssets":{}},"pages-manifest":{"chunks":[14],"assets":["pages-manifest-8ac16b634aef9ae2e64e.js","pages-manifest-8ac16b634aef9ae2e64e.js.map"],"children":{},"childAssets":{}},"pdfjsWorker":{"chunks":[21],"assets":["21-83f4b9fed6059364eea3.js","21-83f4b9fed6059364eea3.js.map"],"children":{},"childAssets":{}}},"assetsByChunkName":{"app":["webpack-runtime-2a6f68dc67aea08bf991.js","app-f94ae40fe74996f430c9.js"],"component---src-templates-post-jsx":["styles.b004dd8d4d17221ed601.css","styles-5767387eccded947114a.js","1-2dce45b6c53bff1bbba8.js","2-4aefba31d5b56627ae14.js","16-666c10685e60702f38b2.js","component---src-templates-post-jsx-b674d58c0a60dbcb822f.js"],"component---src-templates-tag-jsx":["styles.b004dd8d4d17221ed601.css","styles-5767387eccded947114a.js","1-2dce45b6c53bff1bbba8.js","2-4aefba31d5b56627ae14.js","3-617b385cf3249e7667b6.js","component---src-templates-tag-jsx-2af747ec75d0e3fd3490.js"],"component---src-templates-category-jsx":["styles.b004dd8d4d17221ed601.css","styles-5767387eccded947114a.js","1-2dce45b6c53bff1bbba8.js","2-4aefba31d5b56627ae14.js","3-617b385cf3249e7667b6.js","component---src-templates-category-jsx-157bacaf24236da2ba68.js"],"component---src-templates-about-jsx":["styles.b004dd8d4d17221ed601.css","styles-5767387eccded947114a.js","1-2dce45b6c53bff1bbba8.js","component---src-templates-about-jsx-3755af25d0144ff749d4.js"],"component---src-pages-blog-jsx":["styles.b004dd8d4d17221ed601.css","styles-5767387eccded947114a.js","1-2dce45b6c53bff1bbba8.js","2-4aefba31d5b56627ae14.js","3-617b385cf3249e7667b6.js","component---src-pages-blog-jsx-899d090f3229500a45b3.js"],"component---src-pages-contact-jsx":["styles.b004dd8d4d17221ed601.css","styles-5767387eccded947114a.js","1-2dce45b6c53bff1bbba8.js","4-475dab03c6ac083504a6.js","17-770f5289fa9f53f65f88.js","component---src-pages-contact-jsx-cc8ecbea0ae01bc744fc.js"],"component---src-pages-index-jsx":["styles.b004dd8d4d17221ed601.css","styles-5767387eccded947114a.js","1-2dce45b6c53bff1bbba8.js","4-475dab03c6ac083504a6.js","20-81f54fec9d476b38d4d9.js","component---src-pages-index-jsx-13b1b4ed693638807161.js"],"component---src-pages-resume-jsx":["styles.b004dd8d4d17221ed601.css","styles-5767387eccded947114a.js","1-2dce45b6c53bff1bbba8.js","18-13d57edf398610c1aa01.js","component---src-pages-resume-jsx-7a1eb7995620c0320d38.js"],"pages-manifest":["pages-manifest-8ac16b634aef9ae2e64e.js"],"pdfjsWorker":["21-83f4b9fed6059364eea3.js"]}}